html_img/__init__.py
html_img/render.py
html_img-0.0.1.dist-info/LICENSE
html_img-0.0.1.dist-info/METADATA
html_img-0.0.1.dist-info/WHEEL
html_img-0.0.1.dist-info/top_level.txt
html_img-0.0.1.dist-info/RECORD
