Metadata-Version: 2.1
Name: html-img
Version: 0.0.1
Summary: A small utils package for generating html with images
Home-page: https://github.com/jaclu010/html-img
Author: Jacob Lundberg
Author-email: jacob.lundberg93@gmail.com
License: UNKNOWN
Project-URL: Bug Tracker, https://github.com/jaclu010/html-img/issues
Platform: UNKNOWN
Classifier: Programming Language :: Python :: 3
Classifier: License :: OSI Approved :: MIT License
Classifier: Operating System :: OS Independent
Classifier: Topic :: Utilities
Requires-Python: >=3.6
